{"type": "FeatureCollection", "features": [{"type": "Feature", "properties": {"STATEFP": "06", "PLACEFP": "55506", "PLACENS": "02585435", "GEOID": "0655506", "NAME": "Panorama Heights", "NAMELSAD": "Panorama Heights CDP", "LSAD": "57", "CLASSFP": "U1", "PCICBSA": "N", "PCINECTA": "N", "MTFCC": "G4210", "FUNCSTAT": "S", "ALAND": 1230480, "AWATER": 0, "INTPTLAT": "+35.8067676", "INTPTLON": "-118.6270528"}, "geometry": {"type": "Polygon", "coordinates": [[[-118.635552, 35.809732], [-118.628425, 35.809724], [-118.628438, 35.810692], [-118.628388, 35.810896], [-118.619214, 35.811218], [-118.619173, 35.808052], [-118.619214, 35.803162], [-118.629556, 35.802882], [-118.635504, 35.803001], [-118.635664, 35.808221], [-118.635552, 35.809732]]]}}]}