{"type": "FeatureCollection", "features": [{"type": "Feature", "properties": {"STATEFP": "48", "PLACEFP": "71289", "PLACENS": "02586994", "GEOID": "4871289", "NAME": "Sunset Acres", "NAMELSAD": "Sunset Acres CDP", "LSAD": "57", "CLASSFP": "U1", "PCICBSA": "N", "PCINECTA": "N", "MTFCC": "G4210", "FUNCSTAT": "S", "ALAND": 43829, "AWATER": 0, "INTPTLAT": "+27.7941655", "INTPTLON": "-099.4566034"}, "geometry": {"type": "Polygon", "coordinates": [[[-99.458722, 27.793722], [-99.458585, 27.793784], [-99.454962, 27.795457], [-99.454642, 27.794933], [-99.454466, 27.794644], [-99.458053, 27.79294], [-99.458207, 27.792869], [-99.458444, 27.79326], [-99.458464, 27.793294], [-99.458603, 27.793524], [-99.458722, 27.793722]]]}}]}